fluid/__init__.py
fluid/api_client.py
fluid/configuration.py
fluid/exceptions.py
fluid/rest.py
fluid/api/__init__.py
fluid/api/fluid_client.py
fluid/api/fluid_dataflow.py
fluid/api/fluid_k8s_client.py
fluid/constants/__init__.py
fluid/constants/constants.py
fluid/io/__init__.py
fluid/io/filesystem.py
fluid/models/__init__.py
fluid/models/affinity_strategy.py
fluid/models/alluxio_comp_template_spec.py
fluid/models/alluxio_comp_template_spec.py~merged
fluid/models/alluxio_fuse_spec.py
fluid/models/alluxio_fuse_spec.py~merged
fluid/models/alluxio_runtime.py
fluid/models/alluxio_runtime.py~merged
fluid/models/alluxio_runtime_list.py
fluid/models/alluxio_runtime_list.py~merged
fluid/models/alluxio_runtime_spec.py
fluid/models/alluxio_runtime_spec.py~merged
fluid/models/api_gateway_status.py
fluid/models/api_gateway_status.py~merged
fluid/models/cacheable_node_affinity.py
fluid/models/cacheable_node_affinity.py~merged
fluid/models/clean_cache_policy.py
fluid/models/client_metrics.py
fluid/models/condition.py
fluid/models/condition.py~merged
fluid/models/data.py
fluid/models/data.py~merged
fluid/models/data_backup.py
fluid/models/data_backup.py~merged
fluid/models/data_backup_list.py
fluid/models/data_backup_list.py~merged
fluid/models/data_backup_spec.py
fluid/models/data_backup_spec.py~merged
fluid/models/data_load.py
fluid/models/data_load.py~merged
fluid/models/data_load_list.py
fluid/models/data_load_list.py~merged
fluid/models/data_load_spec.py
fluid/models/data_migrate.py
fluid/models/data_migrate_list.py
fluid/models/data_migrate_spec.py
fluid/models/data_process.py
fluid/models/data_process_list.py
fluid/models/data_process_spec.py
fluid/models/data_restore_location.py
fluid/models/data_restore_location.py~merged
fluid/models/data_to_migrate.py
fluid/models/dataset.py
fluid/models/dataset.py~merged
fluid/models/dataset_condition.py
fluid/models/dataset_condition.py~merged
fluid/models/dataset_list.py
fluid/models/dataset_list.py~merged
fluid_pysdk-1.0.4.dist-info/LICENSE
fluid_pysdk-1.0.4.dist-info/METADATA
fluid_pysdk-1.0.4.dist-info/WHEEL
fluid_pysdk-1.0.4.dist-info/top_level.txt
fluid_pysdk-1.0.4.dist-info/RECORD
