Metadata-Version: 2.1
Name: fluid-pysdk
Version: 1.0.4
Summary: Python SDK for fluid-cloudnative fluid to manage datasets
Author-email: Fluid Authors <fluid.opensource.project@gmail.com>
License: Apache License
Project-URL: Homepage, https://github.com/fluid-cloudnative/fluid-client-python
Project-URL: Issues, https://github.com/fluid-cloudnative/fluid-client-python/issues
Keywords: fluid,kubernetes,data-abstraction,data-pipeline,distributed-cache
Classifier: Development Status :: 3 - Alpha
Classifier: Intended Audience :: Developers
Classifier: License :: OSI Approved :: Apache Software License
Classifier: Operating System :: OS Independent
Classifier: Programming Language :: Python
Classifier: Programming Language :: Python :: 3
Classifier: Programming Language :: Python :: 3 :: Only
Classifier: Programming Language :: Python :: 3.7
Classifier: Programming Language :: Python :: 3.8
Classifier: Programming Language :: Python :: 3.9
Classifier: Programming Language :: Python :: 3.10
Classifier: Topic :: Scientific/Engineering
Classifier: Topic :: Scientific/Engineering :: Artificial Intelligence
Classifier: Topic :: Software Development
Classifier: Topic :: Software Development :: Libraries
Classifier: Topic :: Software Development :: Libraries :: Python Modules
Requires-Python: >=3.7
License-File: LICENSE
Requires-Dist: certifi >=14.05.14
Requires-Dist: six >=1.10
Requires-Dist: python-dateutil >=2.5.3
Requires-Dist: setuptools >=21.0.0
Requires-Dist: urllib3 >=1.15.1
Requires-Dist: kubernetes >=18.20.0
Requires-Dist: fsspec ~=2023.12.2
Requires-Dist: s3fs ~=2023.12.2
Requires-Dist: python-dateutil ~=2.8.2
Requires-Dist: future ; python_version <= "2.7"
